{
  "format" : "10.0.0",
  "id" : "17D8046C692CA8F3",
  "kind" : "CALLABLE_SUB",
  "config" : {
    "data" : "com.axonivy.connector.twitter.TwitterData"
  },
  "elements" : [ {
      "id" : "f0",
      "type" : "CallSubStart",
      "name" : "findUser(String)",
      "config" : {
        "callSignature" : "findUser",
        "input" : {
          "params" : [
            { "name" : "username", "type" : "String", "desc" : "The user which you want to find in Twitter" }
          ],
          "map" : {
            "out.username" : "param.username"
          }
        },
        "result" : {
          "params" : [
            { "name" : "user", "type" : "com.twitter.api.client.User", "desc" : "The user which was found by the request" }
          ],
          "map" : {
            "result.user" : "in.user"
          }
        },
        "tags" : "CONNECTOR"
      },
      "visual" : {
        "at" : { "x" : 96, "y" : 64 },
        "labelOffset" : { "x" : 8, "y" : 43 },
        "icon" : "res:/webContent/icons/twitter.png?small"
      },
      "connect" : { "id" : "f4", "to" : "f3" }
    }, {
      "id" : "f1",
      "type" : "CallSubEnd",
      "visual" : {
        "at" : { "x" : 352, "y" : 64 }
      }
    }, {
      "id" : "f3",
      "type" : "RestClientCall",
      "name" : "Twitter API (Twitter API v2)",
      "config" : {
        "path" : "/2/users/by/username/{username}",
        "clientId" : "0b74edb8-5459-4ccc-aac7-505531e06398",
        "clientErrorCode" : "ivy:error:rest:client",
        "queryParams" : {
          "expansions" : "",
          "tweet.fields" : "",
          "user.fields" : ""
        },
        "statusErrorCode" : "ivy:error:rest:client",
        "responseMapping" : {
          "out.user" : "result.data"
        },
        "templateParams" : {
          "username" : "in.username"
        },
        "resultType" : "com.twitter.api.client.SingleUserLookupResponse"
      },
      "visual" : {
        "at" : { "x" : 224, "y" : 64 },
        "size" : { "width" : 176, "height" : 60 },
        "icon" : "res:/webContent/icons/twitter.png"
      },
      "connect" : { "id" : "f2", "to" : "f1" }
    }, {
      "id" : "f5",
      "type" : "RestClientCall",
      "name" : "Twitter API (Twitter API v2)",
      "config" : {
        "path" : "/2/tweets/search/recent",
        "clientId" : "0b74edb8-5459-4ccc-aac7-505531e06398",
        "clientErrorCode" : "ivy:error:rest:client",
        "queryParams" : {
          "expansions" : "",
          "tweet.fields" : "",
          "user.fields" : "",
          "query" : "in.query",
          "start_time" : "",
          "end_time" : "",
          "since_id" : "",
          "until_id" : "",
          "max_results" : "",
          "next_token" : "",
          "media.fields" : "",
          "place.fields" : "",
          "poll.fields" : ""
        },
        "statusErrorCode" : "ivy:error:rest:client",
        "responseMapping" : {
          "out.tweets" : "result.data"
        },
        "templateParams" : {
          "username" : ""
        },
        "resultType" : "com.twitter.api.client.TweetSearchResponse"
      },
      "visual" : {
        "at" : { "x" : 224, "y" : 192 },
        "size" : { "width" : 176, "height" : 60 },
        "icon" : "res:/webContent/icons/twitter.png"
      },
      "connect" : { "id" : "f8", "to" : "f7" }
    }, {
      "id" : "f6",
      "type" : "CallSubStart",
      "name" : "findTweets(String)",
      "config" : {
        "callSignature" : "findTweets",
        "input" : {
          "params" : [
            { "name" : "query", "type" : "String", "desc" : "The query to find tweets" }
          ],
          "map" : {
            "out.query" : "param.query"
          }
        },
        "result" : {
          "params" : [
            { "name" : "tweets", "type" : "java.util.List<com.twitter.api.client.Tweet>", "desc" : "The tweets which were found by the request" }
          ],
          "map" : {
            "result.tweets" : "in.tweets"
          }
        },
        "tags" : "CONNECTOR"
      },
      "visual" : {
        "at" : { "x" : 96, "y" : 192 },
        "labelOffset" : { "x" : 16, "y" : 43 },
        "icon" : "res:/webContent/icons/twitter.png?small"
      },
      "connect" : { "id" : "f9", "to" : "f5" }
    }, {
      "id" : "f7",
      "type" : "CallSubEnd",
      "visual" : {
        "at" : { "x" : 352, "y" : 192 }
      }
    } ]
}